README.rst
setup.cfg
setup.py
pyddq/__init__.py
pyddq/core.py
pyddq/exceptions.py
pyddq/jvm_conversions.py
pyddq/reporters.py
pyddq/streams.py
pyddq.egg-info/PKG-INFO
pyddq.egg-info/SOURCES.txt
pyddq.egg-info/dependency_links.txt
pyddq.egg-info/not-zip-safe
pyddq.egg-info/requires.txt
pyddq.egg-info/top_level.txt