Metadata-Version: 1.1
Name: pyddq
Version: 4.1.1
Summary: Python API for Drunken Data Quality
Home-page: https://github.com/FRosner/drunken-data-quality#python-api-1
Author: Aleksandr Sorokoumov
Author-email: aleksandr.sorokoumov@gmail.com
License: Apache License Version 2.0
Platform: UNKNOWN
Classifier: Development Status :: 4 - Beta
Classifier: Programming Language :: Python
